{"name": "Hans-B\u00f6ckler-Schule -Sporthalle- (401)", "type": "Sporthalle", "description": "Dreifachhalle", "address": {"street": "Hoffschultestr. 25", "zip": "48155", "city": "M\u00fcnster"}, "properties": {"construction_year": "1979", "Mo 08:00-09:30": {"segment": "Segment 3", "activity": "", "field": "Schulsport", "club": "", "comment": ""}, "Mo 09:45-11:15": {"segment": "Segment 3", "activity": "", "field": "Schulsport", "club": "", "comment": ""}, "Mo 10:00-11:30": {"segment": "Segment 2", "activity": "", "field": "Schulsport", "club": "Gesamtschule M\u00fcnster-Ost (842)", "comment": ""}, "Mo 11:40-13:10": {"segment": "Segment 3", "activity": "", "field": "Schulsport", "club": "Gesamtschule M\u00fcnster-Ost (842)", "comment": ""}, "Mo 13:15-14:45": {"segment": "Segment 3", "activity": "", "field": "Schulsport", "club": "", "comment": ""}, "Mo 15:00-16:30": {"segment": "Segment 3", "activity": "", "field": "Schulsport", "club": "", "comment": ""}, "Mo 16:30-17:30": {"segment": "Gesamtspielfl\u00e4che", "activity": "Handball", "field": "Wettkampfsport", "club": "DJK Sparta M\u00fcnster e. V.", "comment": "Minis"}, "Mo 17:30-19:00": {"segment": "Gesamtspielfl\u00e4che", "activity": "Handball", "field": "Wettkampfsport", "club": "DJK Sparta M\u00fcnster e. V.", "comment": "MJB"}, "Mo 19:00-20:30": {"segment": "Gesamtspielfl\u00e4che", "activity": "Handball", "field": "Wettkampfsport", "club": "Sportverein Adler M\u00fcnster e.V.", "comment": "1./2. Herren"}, "Mo 20:30-22:00": {"segment": "Gesamtspielfl\u00e4che", "activity": "Handball", "field": "Wettkampfsport", "club": "Sportverein Adler M\u00fcnster e.V.", "comment": "Damen"}, "Di 08:00-09:30": {"segment": "Segment 3", "activity": "", "field": "Schulsport", "club": "", "comment": ""}, "Di 09:45-11:15": {"segment": "Segment 3", "activity": "", "field": "Schulsport", "club": "", "comment": ""}, "Di 11:30-13:00": {"segment": "Segment 3", "activity": "", "field": "Schulsport", "club": "", "comment": ""}, "Di 13:15-14:45": {"segment": "Segment 3", "activity": "", "field": "Schulsport", "club": "", "comment": ""}, "Di 15:00-16:30": {"segment": "Segment 3", "activity": "", "field": "Schulsport", "club": "", "comment": ""}, "Di 16:30-18:00": {"segment": "Gesamtspielfl\u00e4che", "activity": "Handball", "field": "Wettkampfsport", "club": "DJK Sparta M\u00fcnster e. V.", "comment": "MJE"}, "Di 18:00-19:00": {"segment": "Gesamtspielfl\u00e4che", "activity": "Handball", "field": "Wettkampfsport", "club": "DJK Sparta M\u00fcnster e. V.", "comment": "MJC 2 / MJC 3"}, "Di 19:00-19:30": {"segment": "Gesamtspielfl\u00e4che", "activity": "Handball", "field": "Wettkampfsport", "club": "DJK Sparta M\u00fcnster e. V.", "comment": "MJC 2 / MJC 3/ WJB 2"}, "Di 19:30-20:30": {"segment": "Gesamtspielfl\u00e4che", "activity": "Handball", "field": "Wettkampfsport", "club": "DJK Sparta M\u00fcnster e. V.", "comment": "WJB 1 + WJB 2"}, "Di 20:30-22:30": {"segment": "Gesamtspielfl\u00e4che", "activity": "Handball", "field": "Wettkampfsport", "club": "DJK Sparta M\u00fcnster e. V.", "comment": "1. Herren"}, "Mi 08:00-09:30": {"segment": "Segment 3", "activity": "", "field": "Schulsport", "club": "", "comment": ""}, "Mi 09:45-11:15": {"segment": "Segment 3", "activity": "", "field": "Schulsport", "club": "", "comment": ""}, "Mi 11:30-13:00": {"segment": "Segment 2", "activity": "", "field": "Schulsport", "club": "", "comment": ""}, "Mi 11:40-13:10": {"segment": "Segment 3", "activity": "", "field": "Schulsport", "club": "Gesamtschule M\u00fcnster-Ost (842)", "comment": ""}, "Mi 13:15-14:15": {"segment": "Segment 3", "activity": "", "field": "Schulsport", "club": "", "comment": ""}, "Mi 14:15-15:45": {"segment": "Segment 3", "activity": "", "field": "Schulsport", "club": "Gesamtschule M\u00fcnster-Ost (842)", "comment": ""}, "Mi 15:45-16:30": {"segment": "Segment 3", "activity": "", "field": "Lehrerarbeitsgemein", "club": "", "comment": "Lehrersport"}, "Mi 16:30-18:00": {"segment": "Segment 3", "activity": "", "field": "Lehrerarbeitsgemein", "club": "", "comment": "Lehrersport"}, "Mi 18:00-20:00": {"segment": "Gesamtspielfl\u00e4che", "activity": "Handball", "field": "Wettkampfsport", "club": "Sportverein Adler M\u00fcnster e.V.", "comment": "1. Damen/ 2. Herren"}, "Mi 20:00-22:30": {"segment": "Gesamtspielfl\u00e4che", "activity": "Handball", "field": "Wettkampfsport", "club": "Sportverein Adler M\u00fcnster e.V.", "comment": "1. Herren"}, "Do 08:00-09:30": {"segment": "Segment 3", "activity": "", "field": "Schulsport", "club": "", "comment": ""}, "Do 09:45-11:15": {"segment": "Segment 3", "activity": "", "field": "Schulsport", "club": "", "comment": ""}, "Do 11:30-13:00": {"segment": "Segment 3", "activity": "", "field": "Schulsport", "club": "", "comment": ""}, "Do 11:40-13:10": {"segment": "Segment 2", "activity": "", "field": "Schulsport", "club": "Gesamtschule M\u00fcnster-Ost (842)", "comment": ""}, "Do 13:15-14:45": {"segment": "Segment 3", "activity": "", "field": "Schulsport", "club": "", "comment": ""}, "Do 15:00-16:30": {"segment": "Gesamtspielfl\u00e4che", "activity": "", "field": "Schulsport", "club": "", "comment": "Vormerkung Gesamtschule MS-Ost"}, "Do 16:30-17:30": {"segment": "Gesamtspielfl\u00e4che", "activity": "Handball", "field": "Wettkampfsport", "club": "DJK Sparta M\u00fcnster e. V.", "comment": "MJD 2"}, "Do 17:30-18:00": {"segment": "Gesamtspielfl\u00e4che", "activity": "Handball", "field": "Wettkampfsport", "club": "DJK Sparta M\u00fcnster e. V.", "comment": "MJD 2 + WJB 2"}, "Do 18:00-19:00": {"segment": "Gesamtspielfl\u00e4che", "activity": "Handball", "field": "Wettkampfsport", "club": "DJK Sparta M\u00fcnster e. V.", "comment": "WJB 2"}, "Do 19:00-20:30": {"segment": "Gesamtspielfl\u00e4che", "activity": "Handball", "field": "Wettkampfsport", "club": "DJK Sparta M\u00fcnster e. V.", "comment": "1. Herren"}, "Do 20:30-22:30": {"segment": "Gesamtspielfl\u00e4che", "activity": "Handball", "field": "Wettkampfsport", "club": "DJK Sparta M\u00fcnster e. V.", "comment": "Herren 2"}, "Fr 08:00-09:30": {"segment": "Segment 3", "activity": "", "field": "Schulsport", "club": "", "comment": ""}, "Fr 09:45-11:15": {"segment": "Segment 3", "activity": "", "field": "Schulsport", "club": "", "comment": ""}, "Fr 11:30-13:00": {"segment": "Segment 3", "activity": "", "field": "Schulsport", "club": "", "comment": ""}, "Fr 13:15-14:45": {"segment": "Segment 3", "activity": "", "field": "Schulsport", "club": "", "comment": ""}, "Fr 15:00-16:30": {"segment": "Segment 3", "activity": "", "field": "Schulsport", "club": "", "comment": ""}, "Fr 16:30-17:30": {"segment": "Gesamtspielfl\u00e4che", "activity": "Handball", "field": "Wettkampfsport", "club": "DJK Sparta M\u00fcnster e. V.", "comment": "WJC / MJE"}, "Fr 17:30-19:00": {"segment": "Gesamtspielfl\u00e4che", "activity": "Handball", "field": "Wettkampfsport", "club": "DJK Sparta M\u00fcnster e. V.", "comment": "MJA 2"}, "Fr 19:00-20:30": {"segment": "Gesamtspielfl\u00e4che", "activity": "Handball", "field": "Wettkampfsport", "club": "DJK Sparta M\u00fcnster e. V.", "comment": "1. Damen"}, "Fr 20:30-22:30": {"segment": "Gesamtspielfl\u00e4che", "activity": "Hockey", "field": "Wettkampfsport", "club": "Tennis-und Hockey-Club M\u00fcnster e.V.", "comment": "3. Herren"}, "Fr 20:30-22:00": {"segment": "Gesamtspielfl\u00e4che", "activity": "Basketball", "field": "Breitensport", "club": "Sportclub Westfalia Kinderhaus e.V.", "comment": "5.Herren"}}}